master_converter.py
master_converter-3.0.4.dist-info/LICENSE
master_converter-3.0.4.dist-info/METADATA
master_converter-3.0.4.dist-info/WHEEL
master_converter-3.0.4.dist-info/top_level.txt
master_converter-3.0.4.dist-info/RECORD
