Metadata-Version: 2.1
Name: master_converter
Version: 3.0.4
Summary: A package for converting units
Author-email: Spyridon Coryell <master_converter@protonmail.com>
License: Copyright (c) 2024 Spyridon Coryell
Project-URL: Homepage, https://github.com/SmallCoder13/master-converter
Project-URL: Issues, https://github.com/SmallCoder13/master-converter/issues
License-File: LICENSE
